COPYING
MANIFEST.in
README.md
setup.py
sortcss.py
sortcss.py.egg-info/PKG-INFO
sortcss.py.egg-info/SOURCES.txt
sortcss.py.egg-info/dependency_links.txt
sortcss.py.egg-info/requires.txt
sortcss.py.egg-info/top_level.txt
test/test.py
test/case/test-0001-0.css
test/case/test-0001-1.css
test/case/test-0002-0.css
test/case/test-0002-1.css
test/case/test-0003-0.css
test/case/test-0003-1.css
test/case/test-0004-0.css
test/case/test-0004-1.css
test/case/test-0005-0.css
test/case/test-0005-1.css
test/case/test-0006-0.css
test/case/test-0006-1.css
test/case/test-0006.arg
test/case/test-0007-0.css
test/case/test-0007-1.css
test/case/test-0008-0.css
test/case/test-0008-1.css
test/case/test-0009-0.css
test/case/test-0009-1.css