Metadata-Version: 1.1
Name: sortcss.py
Version: 0.1.2
Summary: CSS Property Sorter Script
Home-page: https://github.com/livibetter/css-prop-sorter
Author: Yu-Jie Lin
Author-email: livibetter@gmail.com
License: MIT
Platform: UNKNOWN
Classifier: Development Status :: 3 - Alpha
Classifier: Environment :: Console
Classifier: Intended Audience :: Developers
Classifier: License :: OSI Approved :: MIT License
Classifier: Natural Language :: English
Classifier: Operating System :: POSIX
Classifier: Programming Language :: Python :: 2.7
Classifier: Programming Language :: Python :: 3
Classifier: Topic :: Utilities
